rucio_jupyterlab/__init__.py
rucio_jupyterlab/_version.py
rucio_jupyterlab/db.py
rucio_jupyterlab/entity.py
rucio_jupyterlab/server.py
rucio_jupyterlab/utils.py
rucio_jupyterlab/config/__init__.py
rucio_jupyterlab/config/config.py
rucio_jupyterlab/config/schema.py
rucio_jupyterlab/handlers/__init__.py
rucio_jupyterlab/handlers/auth_config.py
rucio_jupyterlab/handlers/base.py
rucio_jupyterlab/handlers/did_browser.py
rucio_jupyterlab/handlers/did_details.py
rucio_jupyterlab/handlers/did_make_available.py
rucio_jupyterlab/handlers/did_search.py
rucio_jupyterlab/handlers/file_browser.py
rucio_jupyterlab/handlers/handlers.py
rucio_jupyterlab/handlers/instances.py
rucio_jupyterlab/handlers/oidc_auth_check.py
rucio_jupyterlab/handlers/open_replication_rule.py
rucio_jupyterlab/handlers/purge_cache.py
rucio_jupyterlab/kernels/__init__.py
rucio_jupyterlab/kernels/ipython/__init__.py
rucio_jupyterlab/kernels/ipython/types.py
rucio_jupyterlab/labextension/package.json
rucio_jupyterlab/labextension/static/135.50004f3b855a9257e8ed.js
rucio_jupyterlab/labextension/static/392.09671b4bdc4c4bdedb71.js
rucio_jupyterlab/labextension/static/429.407b01bdf4a8a104bc25.js
rucio_jupyterlab/labextension/static/465.35634742734dc7d3c691.js
rucio_jupyterlab/labextension/static/549.b20ee4a7cef036cb0e44.js
rucio_jupyterlab/labextension/static/594.bb16e01fd6647f801c63.js
rucio_jupyterlab/labextension/static/608.78d6a56a4ed664de03b6.js
rucio_jupyterlab/labextension/static/608.78d6a56a4ed664de03b6.js.LICENSE.txt
rucio_jupyterlab/labextension/static/728.7ca414f1e7ce693f2c02.js
rucio_jupyterlab/labextension/static/769.097a38159e46c8e332cd.js
rucio_jupyterlab/labextension/static/855.fd11e9ed650c9ff9d8e6.js
rucio_jupyterlab/labextension/static/95.2a53a21fe091e0fa6c51.js
rucio_jupyterlab/labextension/static/95.2a53a21fe091e0fa6c51.js.LICENSE.txt
rucio_jupyterlab/labextension/static/956.49ad8cd38c6eca8f55e9.js
rucio_jupyterlab/labextension/static/956.49ad8cd38c6eca8f55e9.js.LICENSE.txt
rucio_jupyterlab-0.7.0.dist-info/AUTHORS.md
rucio_jupyterlab-0.7.0.dist-info/LICENSE
rucio_jupyterlab-0.7.0.dist-info/METADATA
rucio_jupyterlab-0.7.0.dist-info/WHEEL
rucio_jupyterlab-0.7.0.dist-info/top_level.txt
rucio_jupyterlab-0.7.0.dist-info/RECORD
