Metadata-Version: 2.1
Name: rucio-jupyterlab
Version: 0.7.0
Summary: JupyterLab extension for integrating Rucio
Home-page: https://github.com/rucio/jupyterlab-extension
Author: Muhammad Aditya Hilmy
Author-email: mhilmy@hey.com
License: Apache-2.0
Keywords: Jupyter,JupyterLab,JupyterLab3
Platform: Linux
Platform: Mac OS X
Platform: Windows
Classifier: License :: OSI Approved :: Apache Software License
Classifier: Programming Language :: Python
Classifier: Programming Language :: Python :: 3
Classifier: Programming Language :: Python :: 3.6
Classifier: Programming Language :: Python :: 3.7
Classifier: Programming Language :: Python :: 3.8
Classifier: Programming Language :: Python :: 3.9
Classifier: Framework :: Jupyter
Requires-Python: >=3.6
License-File: LICENSE
License-File: AUTHORS.md
Requires-Dist: jupyter-server (<2,>=1.6)
Requires-Dist: requests (~=2.25.0)
Requires-Dist: peewee (~=3.14.0)
Requires-Dist: jsonschema (~=3.2.0)
Requires-Dist: psutil (~=5.8.0)
Requires-Dist: rucio-clients (~=1.26.0)
